[{"No": 1, "IndexSummaryID": 85528, "Date": "2016-10-21T00:00:00", "IndexCode": "COMPOSITE", "Previous": 5403.69, "Highest": 5416.952, "Lowest": 5395.423, "Close": 5409.243, "NumberOfStock": 538.0, "Change": 5.553, "Volume": 12227740495.0, "Value": 6001311697877.0, "Frequency": 240700.0, "MarketCapital": 5848966959799100.0}, {"No": 2, "IndexSummaryID": 85539, "Date": "2016-10-21T00:00:00", "IndexCode": "LQ45", "Previous": 929.817, "Highest": 932.176, "Lowest": 927.928, "Close": 930.462, "NumberOfStock": 45.0, "Change": 0.645, "Volume": 3800360076.0, "Value": 3582578489624.0, "Frequency": 101207.0, "MarketCapital": 3978801533394650.0}, {"No": 3, "IndexSummaryID": 85548, "Date": "2016-10-21T00:00:00", "IndexCode": "IDX30", "Previous": 502.41, "Highest": 503.765, "Lowest": 501.439, "Close": 503.463, "NumberOfStock": 30.0, "Change": 1.053, "Volume": 764607843.0, "Value": 2662478962579.0, "Frequency": 69546.0, "MarketCapital": 3725081633195620.0}, {"No": 4, "IndexSummaryID": 85547, "Date": "2016-10-21T00:00:00", "IndexCode": "ISSI", "Previous": 178.281, "Highest": 178.757, "Lowest": 177.994, "Close": 178.059, "NumberOfStock": 311.0, "Change": -0.222, "Volume": 3663629811.0, "Value": 3767410821304.0, "Frequency": 143579.0, "MarketCapital": 3270137129017370.0}, {"No": 5, "IndexSummaryID": 85540, "Date": "2016-10-21T00:00:00", "IndexCode": "JII", "Previous": 741.069, "Highest": 744.032, "Lowest": 739.418, "Close": 739.418, "NumberOfStock": 30.0, "Change": -1.651, "Volume": 748090586.0, "Value": 2120669012474.0, "Frequency": 60848.0, "MarketCapital": 2187325292927200.0}, {"No": 6, "IndexSummaryID": 85541, "Date": "2016-10-21T00:00:00", "IndexCode": "MBX", "Previous": 1544.826, "Highest": 1549.19, "Lowest": 1543.128, "Close": 1547.364, "NumberOfStock": 281.0, "Change": 2.538, "Volume": 5711179651.0, "Value": 4629417341795.0, "Frequency": 186981.0, "MarketCapital": 5230522167871860.0}, {"No": 7, "IndexSummaryID": 85542, "Date": "2016-10-21T00:00:00", "IndexCode": "DBX", "Previous": 796.639, "Highest": 797.543, "Lowest": 790.604, "Close": 793.368, "NumberOfStock": 257.0, "Change": -3.271, "Volume": 6516560844.0, "Value": 1371894356082.0, "Frequency": 53719.0, "MarketCapital": 618444791927237.0}, {"No": 8, "IndexSummaryID": 85543, "Date": "2016-10-21T00:00:00", "IndexCode": "KOMPAS100", "Previous": 1163.325, "Highest": 1166.454, "Lowest": 1161.319, "Close": 1164.617, "NumberOfStock": 100.0, "Change": 1.292, "Volume": 6715868195.0, "Value": 4973083263074.0, "Frequency": 180951.0, "MarketCapital": 4531239469044910.0}, {"No": 9, "IndexSummaryID": 85549, "Date": "2016-10-21T00:00:00", "IndexCode": "INFOBANK15", "Previous": 609.309, "Highest": 612.722, "Lowest": 608.752, "Close": 610.969, "NumberOfStock": 15.0, "Change": 1.66, "Volume": 223411005.0, "Value": 833678895950.0, "Frequency": 14407.0, "MarketCapital": 1201079233372630.0}, {"No": 10, "IndexSummaryID": 85544, "Date": "2016-10-21T00:00:00", "IndexCode": "BISNIS-27", "Previous": 480.172, "Highest": 482.226, "Lowest": 479.502, "Close": 479.502, "NumberOfStock": 27.0, "Change": -0.67, "Volume": 633070372.0, "Value": 2392427263364.0, "Frequency": 60902.0, "MarketCapital": 2844984221881680.0}, {"No": 11, "IndexSummaryID": 85552, "Date": "2016-10-21T00:00:00", "IndexCode": "Investor33", "Previous": 386.235, "Highest": 387.844, "Lowest": 385.908, "Close": 386.398, "NumberOfStock": 33.0, "Change": 0.163, "Volume": 822747575.0, "Value": 2324696494824.0, "Frequency": 64551.0, "MarketCapital": 3150746121810260.0}, {"No": 12, "IndexSummaryID": 85546, "Date": "2016-10-21T00:00:00", "IndexCode": "SRI-KEHATI", "Previous": 322.104, "Highest": 323.377, "Lowest": 321.755, "Close": 322.124, "NumberOfStock": 25.0, "Change": 0.02, "Volume": 337645626.0, "Value": 1780668462480.0, "Frequency": 33676.0, "MarketCapital": 2750052693614180.0}, {"No": 13, "IndexSummaryID": 85550, "Date": "2016-10-21T00:00:00", "IndexCode": "SMinfra18", "Previous": 352.045, "Highest": 354.518, "Lowest": 351.739, "Close": 352.366, "NumberOfStock": 18.0, "Change": 0.321, "Volume": 221282912.0, "Value": 955509873700.0, "Frequency": 24922.0, "MarketCapital": 894648324344725.0}, {"No": 14, "IndexSummaryID": 85551, "Date": "2016-10-21T00:00:00", "IndexCode": "MNC36", "Previous": 307.387, "Highest": 308.479, "Lowest": 307.147, "Close": 307.978, "NumberOfStock": 36.0, "Change": 0.591, "Volume": 820173215.0, "Value": 2682751404835.0, "Frequency": 67988.0, "MarketCapital": 3384778861484950.0}, {"No": 15, "IndexSummaryID": 85545, "Date": "2016-10-21T00:00:00", "IndexCode": "PEFINDO25", "Previous": 406.402, "Highest": 408.473, "Lowest": 405.222, "Close": 407.073, "NumberOfStock": 25.0, "Change": 0.671, "Volume": 371940500.0, "Value": 291757757000.0, "Frequency": 17010.0, "MarketCapital": 258044892205212.0}, {"No": 16, "IndexSummaryID": 85529, "Date": "2016-10-21T00:00:00", "IndexCode": "AGRI", "Previous": 1803.567, "Highest": 1805.5, "Lowest": 1782.38, "Close": 1782.38, "NumberOfStock": 21.0, "Change": -21.187, "Volume": 325668147.0, "Value": 213026608445.0, "Frequency": 9241.0, "MarketCapital": 131184161181395.0}, {"No": 17, "IndexSummaryID": 85530, "Date": "2016-10-21T00:00:00", "IndexCode": "MINING", "Previous": 1274.614, "Highest": 1277.78, "Lowest": 1252.334, "Close": 1256.647, "NumberOfStock": 43.0, "Change": -17.967, "Volume": 1756303737.0, "Value": 814913115800.0, "Frequency": 41258.0, "MarketCapital": 259311623906442.0}, {"No": 18, "IndexSummaryID": 85531, "Date": "2016-10-21T00:00:00", "IndexCode": "BASIC-IND", "Previous": 524.662, "Highest": 526.391, "Lowest": 520.114, "Close": 526.266, "NumberOfStock": 66.0, "Change": 1.604, "Volume": 513079550.0, "Value": 625511467600.0, "Frequency": 21679.0, "MarketCapital": 388614405879806.0}, {"No": 19, "IndexSummaryID": 85532, "Date": "2016-10-21T00:00:00", "IndexCode": "MISC-IND", "Previous": 1386.796, "Highest": 1394.474, "Lowest": 1381.478, "Close": 1385.166, "NumberOfStock": 42.0, "Change": -1.63, "Volume": 361280409.0, "Value": 207845857825.0, "Frequency": 20723.0, "MarketCapital": 397892424648972.0}, {"No": 20, "IndexSummaryID": 85533, "Date": "2016-10-21T00:00:00", "IndexCode": "CONSUMER", "Previous": 2498.918, "Highest": 2512.251, "Lowest": 2487.847, "Close": 2512.251, "NumberOfStock": 39.0, "Change": 13.333, "Volume": 66798451.0, "Value": 520475743950.0, "Frequency": 13762.0, "MarketCapital": 1389224452718950.0}, {"No": 21, "IndexSummaryID": 85534, "Date": "2016-10-21T00:00:00", "IndexCode": "PROPERTY", "Previous": 564.82, "Highest": 567.981, "Lowest": 565.074, "Close": 565.074, "NumberOfStock": 63.0, "Change": 0.254, "Volume": 6186345406.0, "Value": 1390262941860.0, "Frequency": 44593.0, "MarketCapital": 454178921570222.0}, {"No": 22, "IndexSummaryID": 85535, "Date": "2016-10-21T00:00:00", "IndexCode": "INFRASTRUC", "Previous": 1100.14, "Highest": 1105.772, "Lowest": 1095.446, "Close": 1101.12, "NumberOfStock": 56.0, "Change": 0.98, "Volume": 613955697.0, "Value": 523299344000.0, "Frequency": 22213.0, "MarketCapital": 750376777506516.0}, {"No": 23, "IndexSummaryID": 85536, "Date": "2016-10-21T00:00:00", "IndexCode": "FINANCE", "Previous": 800.991, "Highest": 805.048, "Lowest": 800.433, "Close": 802.658, "NumberOfStock": 88.0, "Change": 1.667, "Volume": 758195553.0, "Value": 980083700891.0, "Frequency": 22136.0, "MarketCapital": 1458597697326260.0}, {"No": 24, "IndexSummaryID": 85537, "Date": "2016-10-21T00:00:00", "IndexCode": "TRADE", "Previous": 863.96, "Highest": 869.31, "Lowest": 861.96, "Close": 862.989, "NumberOfStock": 120.0, "Change": -0.971, "Volume": 1646113545.0, "Value": 725892917506.0, "Frequency": 45095.0, "MarketCapital": 619586495060540.0}, {"No": 25, "IndexSummaryID": 85538, "Date": "2016-10-21T00:00:00", "IndexCode": "MANUFACTUR", "Previous": 1428.81, "Highest": 1434.142, "Lowest": 1424.498, "Close": 1434.142, "NumberOfStock": 147.0, "Change": 5.332, "Volume": 941158410.0, "Value": 1353833069375.0, "Frequency": 56164.0, "MarketCapital": 2175731283247730.0}]