[{"No": 1, "IndexSummaryID": 79628, "Date": "2016-05-13T00:00:00", "IndexCode": "COMPOSITE", "Previous": 4803.322, "Highest": 4803.004, "Lowest": 4745.909, "Close": 4761.715, "NumberOfStock": 528.0, "Change": -41.607, "Volume": 4390616579.0, "Value": 5735423134866.0, "Frequency": 226658.0, "MarketCapital": 5055364503312460.0}, {"No": 2, "IndexSummaryID": 79639, "Date": "2016-05-13T00:00:00", "IndexCode": "LQ45", "Previous": 825.61, "Highest": 825.644, "Lowest": 812.905, "Close": 817.025, "NumberOfStock": 45.0, "Change": -8.585, "Volume": 1469974999.0, "Value": 4351556707115.0, "Frequency": 122194.0, "MarketCapital": 3510810351198940.0}, {"No": 3, "IndexSummaryID": 79648, "Date": "2016-05-13T00:00:00", "IndexCode": "IDX30", "Previous": 434.483, "Highest": 434.256, "Lowest": 425.815, "Close": 428.534, "NumberOfStock": 30.0, "Change": -5.949, "Volume": 912990599.0, "Value": 3432529919915.0, "Frequency": 90515.0, "MarketCapital": 2786086835693310.0}, {"No": 4, "IndexSummaryID": 79647, "Date": "2016-05-13T00:00:00", "IndexCode": "ISSI", "Previous": 156.131, "Highest": 156.278, "Lowest": 153.743, "Close": 154.326, "NumberOfStock": 318.0, "Change": -1.805, "Volume": 3332046792.0, "Value": 4133674038141.0, "Frequency": 163120.0, "MarketCapital": 2768186701903650.0}, {"No": 5, "IndexSummaryID": 79640, "Date": "2016-05-13T00:00:00", "IndexCode": "JII", "Previous": 648.97, "Highest": 649.873, "Lowest": 636.151, "Close": 640.131, "NumberOfStock": 30.0, "Change": -8.839, "Volume": 813335698.0, "Value": 2597077244150.0, "Frequency": 77249.0, "MarketCapital": 1843470509568920.0}, {"No": 6, "IndexSummaryID": 79641, "Date": "2016-05-13T00:00:00", "IndexCode": "MBX", "Previous": 1378.337, "Highest": 1378.056, "Lowest": 1359.938, "Close": 1365.208, "NumberOfStock": 275.0, "Change": -13.129, "Volume": 2870976732.0, "Value": 4850612713790.0, "Frequency": 189468.0, "MarketCapital": 4508288919252190.0}, {"No": 7, "IndexSummaryID": 79642, "Date": "2016-05-13T00:00:00", "IndexCode": "DBX", "Previous": 685.472, "Highest": 686.937, "Lowest": 683.227, "Close": 684.436, "NumberOfStock": 253.0, "Change": -1.036, "Volume": 1519639847.0, "Value": 884810421076.0, "Frequency": 37190.0, "MarketCapital": 547075584060266.0}, {"No": 8, "IndexSummaryID": 79643, "Date": "2016-05-13T00:00:00", "IndexCode": "KOMPAS100", "Previous": 1028.526, "Highest": 1028.277, "Lowest": 1013.717, "Close": 1018.949, "NumberOfStock": 100.0, "Change": -9.577, "Volume": 3069058478.0, "Value": 5231760992871.0, "Frequency": 179683.0, "MarketCapital": 3937928191994360.0}, {"No": 9, "IndexSummaryID": 79649, "Date": "2016-05-13T00:00:00", "IndexCode": "INFOBANK15", "Previous": 504.544, "Highest": 504.54, "Lowest": 495.763, "Close": 499.952, "NumberOfStock": 15.0, "Change": -4.592, "Volume": 152589665.0, "Value": 891694934625.0, "Frequency": 22024.0, "MarketCapital": 997254165517500.0}, {"No": 10, "IndexSummaryID": 79644, "Date": "2016-05-13T00:00:00", "IndexCode": "BISNIS-27", "Previous": 406.24, "Highest": 405.624, "Lowest": 396.927, "Close": 398.561, "NumberOfStock": 27.0, "Change": -7.679, "Volume": 768218697.0, "Value": 3065983244615.0, "Frequency": 81424.0, "MarketCapital": 2360933438061120.0}, {"No": 11, "IndexSummaryID": 79652, "Date": "2016-05-13T00:00:00", "IndexCode": "Investor33", "Previous": 336.103, "Highest": 336.228, "Lowest": 329.822, "Close": 331.821, "NumberOfStock": 33.0, "Change": -4.282, "Volume": 846182411.0, "Value": 3325738087915.0, "Frequency": 90084.0, "MarketCapital": 2706755875961560.0}, {"No": 12, "IndexSummaryID": 79646, "Date": "2016-05-13T00:00:00", "IndexCode": "SRI-KEHATI", "Previous": 277.557, "Highest": 277.764, "Lowest": 272.239, "Close": 274.188, "NumberOfStock": 25.0, "Change": -3.369, "Volume": 830683363.0, "Value": 2865297608275.0, "Frequency": 76472.0, "MarketCapital": 2335991669783520.0}, {"No": 13, "IndexSummaryID": 79650, "Date": "2016-05-13T00:00:00", "IndexCode": "SMinfra18", "Previous": 329.541, "Highest": 331.378, "Lowest": 323.467, "Close": 323.467, "NumberOfStock": 18.0, "Change": -6.074, "Volume": 378376877.0, "Value": 1552005966375.0, "Frequency": 39967.0, "MarketCapital": 811468432086275.0}, {"No": 14, "IndexSummaryID": 79651, "Date": "2016-05-13T00:00:00", "IndexCode": "MNC36", "Previous": 270.011, "Highest": 270.09, "Lowest": 265.246, "Close": 266.808, "NumberOfStock": 36.0, "Change": -3.203, "Volume": 879627469.0, "Value": 3462261116615.0, "Frequency": 91289.0, "MarketCapital": 2932323260153430.0}, {"No": 15, "IndexSummaryID": 79645, "Date": "2016-05-13T00:00:00", "IndexCode": "PEFINDO25", "Previous": 377.694, "Highest": 384.254, "Lowest": 376.71, "Close": 384.254, "NumberOfStock": 25.0, "Change": 6.56, "Volume": 434519870.0, "Value": 433958699600.0, "Frequency": 23338.0, "MarketCapital": 252329881955585.0}, {"No": 16, "IndexSummaryID": 79629, "Date": "2016-05-13T00:00:00", "IndexCode": "AGRI", "Previous": 1778.791, "Highest": 1776.231, "Lowest": 1736.666, "Close": 1743.372, "NumberOfStock": 21.0, "Change": -35.419, "Volume": 145448200.0, "Value": 215787317000.0, "Frequency": 9462.0, "MarketCapital": 119968106539950.0}, {"No": 17, "IndexSummaryID": 79630, "Date": "2016-05-13T00:00:00", "IndexCode": "MINING", "Previous": 953.845, "Highest": 954.814, "Lowest": 941.763, "Close": 942.932, "NumberOfStock": 43.0, "Change": -10.913, "Volume": 644818400.0, "Value": 250784679100.0, "Frequency": 20988.0, "MarketCapital": 187754548853880.0}, {"No": 18, "IndexSummaryID": 79631, "Date": "2016-05-13T00:00:00", "IndexCode": "BASIC-IND", "Previous": 414.437, "Highest": 413.762, "Lowest": 397.837, "Close": 398.058, "NumberOfStock": 64.0, "Change": -16.379, "Volume": 149985248.0, "Value": 323068455140.0, "Frequency": 22386.0, "MarketCapital": 280406456493161.0}, {"No": 19, "IndexSummaryID": 79632, "Date": "2016-05-13T00:00:00", "IndexCode": "MISC-IND", "Previous": 1117.836, "Highest": 1118.022, "Lowest": 1081.165, "Close": 1088.407, "NumberOfStock": 42.0, "Change": -29.429, "Volume": 243412719.0, "Value": 431438185275.0, "Frequency": 12371.0, "MarketCapital": 312574675801061.0}, {"No": 20, "IndexSummaryID": 79633, "Date": "2016-05-13T00:00:00", "IndexCode": "CONSUMER", "Previous": 2366.763, "Highest": 2367.904, "Lowest": 2349.006, "Close": 2362.061, "NumberOfStock": 38.0, "Change": -4.702, "Volume": 131721482.0, "Value": 377881797700.0, "Frequency": 20674.0, "MarketCapital": 1291980761970160.0}, {"No": 21, "IndexSummaryID": 79634, "Date": "2016-05-13T00:00:00", "IndexCode": "PROPERTY", "Previous": 485.987, "Highest": 487.918, "Lowest": 482.139, "Close": 485.671, "NumberOfStock": 60.0, "Change": -0.316, "Volume": 1112487167.0, "Value": 842307895995.0, "Frequency": 41775.0, "MarketCapital": 377142913331931.0}, {"No": 22, "IndexSummaryID": 79635, "Date": "2016-05-13T00:00:00", "IndexCode": "INFRASTRUC", "Previous": 1063.622, "Highest": 1072.353, "Lowest": 1053.72, "Close": 1056.152, "NumberOfStock": 53.0, "Change": -7.47, "Volume": 704094200.0, "Value": 1273835078100.0, "Frequency": 34563.0, "MarketCapital": 688915757935779.0}, {"No": 23, "IndexSummaryID": 79636, "Date": "2016-05-13T00:00:00", "IndexCode": "FINANCE", "Previous": 667.953, "Highest": 668.281, "Lowest": 657.48, "Close": 661.968, "NumberOfStock": 88.0, "Change": -5.985, "Volume": 315735599.0, "Value": 996858451125.0, "Frequency": 31968.0, "MarketCapital": 1187677725781970.0}, {"No": 24, "IndexSummaryID": 79637, "Date": "2016-05-13T00:00:00", "IndexCode": "TRADE", "Previous": 831.732, "Highest": 833.47, "Lowest": 824.583, "Close": 830.165, "NumberOfStock": 119.0, "Change": -1.567, "Volume": 942913564.0, "Value": 1023461275431.0, "Frequency": 32471.0, "MarketCapital": 608943556604568.0}, {"No": 25, "IndexSummaryID": 79638, "Date": "2016-05-13T00:00:00", "IndexCode": "MANUFACTUR", "Previous": 1276.979, "Highest": 1276.268, "Lowest": 1256.362, "Close": 1261.875, "NumberOfStock": 144.0, "Change": -15.104, "Volume": 525119449.0, "Value": 1132388438115.0, "Frequency": 55431.0, "MarketCapital": 1884961894264380.0}]