[{"No": 1, "IndexSummaryID": 69628, "Date": "2015-07-10T00:00:00", "IndexCode": "COMPOSITE", "Previous": 4838.284, "Highest": 4882.641, "Lowest": 4845.785, "Close": 4859.034, "NumberOfStock": 516.0, "Change": 20.75, "Volume": 5655059731.0, "Value": 5742321045102.0, "Frequency": 209162.0, "MarketCapital": 4972249947835630.0}, {"No": 2, "IndexSummaryID": 69639, "Date": "2015-07-10T00:00:00", "IndexCode": "LQ45", "Previous": 824.732, "Highest": 834.804, "Lowest": 825.946, "Close": 829.821, "NumberOfStock": 45.0, "Change": 5.089, "Volume": 1806109863.0, "Value": 4272200722192.0, "Frequency": 110115.0, "MarketCapital": 3092624378987220.0}, {"No": 3, "IndexSummaryID": 69648, "Date": "2015-07-10T00:00:00", "IndexCode": "IDX30", "Previous": 427.124, "Highest": 432.069, "Lowest": 427.627, "Close": 429.585, "NumberOfStock": 30.0, "Change": 2.461, "Volume": 1420346787.0, "Value": 3753649798822.0, "Frequency": 82251.0, "MarketCapital": 2778829982501830.0}, {"No": 4, "IndexSummaryID": 69647, "Date": "2015-07-10T00:00:00", "IndexCode": "ISSI", "Previous": 155.29, "Highest": 156.748, "Lowest": 155.396, "Close": 155.839, "NumberOfStock": 317.0, "Change": 0.549, "Volume": 4035669034.0, "Value": 4290313368880.0, "Frequency": 154239.0, "MarketCapital": 2837230711929780.0}, {"No": 5, "IndexSummaryID": 69640, "Date": "2015-07-10T00:00:00", "IndexCode": "JII", "Previous": 645.585, "Highest": 652.696, "Lowest": 645.482, "Close": 648.742, "NumberOfStock": 30.0, "Change": 3.157, "Volume": 1628692227.0, "Value": 3260345137490.0, "Frequency": 80685.0, "MarketCapital": 1878175216341800.0}, {"No": 6, "IndexSummaryID": 69641, "Date": "2015-07-10T00:00:00", "IndexCode": "MBX", "Previous": 1391.963, "Highest": 1405.472, "Lowest": 1394.202, "Close": 1397.65, "NumberOfStock": 273.0, "Change": 5.687, "Volume": 3828399380.0, "Value": 5042216801642.0, "Frequency": 175607.0, "MarketCapital": 4439903623491540.0}, {"No": 7, "IndexSummaryID": 69642, "Date": "2015-07-10T00:00:00", "IndexCode": "DBX", "Previous": 678.578, "Highest": 682.867, "Lowest": 678.584, "Close": 682.554, "NumberOfStock": 243.0, "Change": 3.976, "Volume": 1826660351.0, "Value": 700104243460.0, "Frequency": 33555.0, "MarketCapital": 532346324344098.0}, {"No": 8, "IndexSummaryID": 69643, "Date": "2015-07-10T00:00:00", "IndexCode": "KOMPAS100", "Previous": 1041.61, "Highest": 1053.506, "Lowest": 1043.46, "Close": 1047.993, "NumberOfStock": 100.0, "Change": 6.383, "Volume": 4144641708.0, "Value": 5164819837302.0, "Frequency": 171544.0, "MarketCapital": 3453809936926490.0}, {"No": 9, "IndexSummaryID": 69649, "Date": "2015-07-10T00:00:00", "IndexCode": "INFOBANK15", "Previous": 527.485, "Highest": 535.291, "Lowest": 528.933, "Close": 532.489, "NumberOfStock": 15.0, "Change": 5.004, "Volume": 111759684.0, "Value": 796326262702.0, "Frequency": 15617.0, "MarketCapital": 1048934860396220.0}, {"No": 10, "IndexSummaryID": 69644, "Date": "2015-07-10T00:00:00", "IndexCode": "BISNIS-27", "Previous": 405.894, "Highest": 410.735, "Lowest": 406.242, "Close": 408.145, "NumberOfStock": 27.0, "Change": 2.251, "Volume": 476383216.0, "Value": 1896342366052.0, "Frequency": 66839.0, "MarketCapital": 2404919664452340.0}, {"No": 11, "IndexSummaryID": 69652, "Date": "2015-07-10T00:00:00", "IndexCode": "Investor33", "Previous": 338.95, "Highest": 342.626, "Lowest": 339.218, "Close": 340.557, "NumberOfStock": 33.0, "Change": 1.607, "Volume": 726070423.0, "Value": 2131462746072.0, "Frequency": 73809.0, "MarketCapital": 2777645146665110.0}, {"No": 12, "IndexSummaryID": 69646, "Date": "2015-07-10T00:00:00", "IndexCode": "SRI-KEHATI", "Previous": 280.214, "Highest": 283.305, "Lowest": 280.329, "Close": 281.693, "NumberOfStock": 25.0, "Change": 1.479, "Volume": 394449077.0, "Value": 1834685929002.0, "Frequency": 60935.0, "MarketCapital": 2368318387983900.0}, {"No": 13, "IndexSummaryID": 69650, "Date": "2015-07-10T00:00:00", "IndexCode": "SMinfra18", "Previous": 323.818, "Highest": 326.454, "Lowest": 323.92, "Close": 324.098, "NumberOfStock": 18.0, "Change": 0.28, "Volume": 325607840.0, "Value": 873523826700.0, "Frequency": 36833.0, "MarketCapital": 818571832666420.0}, {"No": 14, "IndexSummaryID": 69651, "Date": "2015-07-10T00:00:00", "IndexCode": "MNC36", "Previous": 260.483, "Highest": 263.389, "Lowest": 261.167, "Close": 262.393, "NumberOfStock": 36.0, "Change": 1.91, "Volume": 1636562606.0, "Value": 3598442094742.0, "Frequency": 83491.0, "MarketCapital": 2435741368586220.0}, {"No": 15, "IndexSummaryID": 69645, "Date": "2015-07-10T00:00:00", "IndexCode": "PEFINDO25", "Previous": 420.405, "Highest": 424.134, "Lowest": 419.951, "Close": 421.677, "NumberOfStock": 25.0, "Change": 1.272, "Volume": 973492311.0, "Value": 1674591114870.0, "Frequency": 16510.0, "MarketCapital": 141669419637326.0}, {"No": 16, "IndexSummaryID": 69629, "Date": "2015-07-10T00:00:00", "IndexCode": "AGRI", "Previous": 2121.126, "Highest": 2133.512, "Lowest": 2110.725, "Close": 2133.512, "NumberOfStock": 21.0, "Change": 12.386, "Volume": 1028321651.0, "Value": 1689838010170.0, "Frequency": 14597.0, "MarketCapital": 146812972436675.0}, {"No": 17, "IndexSummaryID": 69630, "Date": "2015-07-10T00:00:00", "IndexCode": "MINING", "Previous": 1057.488, "Highest": 1070.464, "Lowest": 1057.84, "Close": 1060.574, "NumberOfStock": 43.0, "Change": 3.086, "Volume": 414169204.0, "Value": 138969816050.0, "Frequency": 15534.0, "MarketCapital": 205143696656474.0}, {"No": 18, "IndexSummaryID": 69631, "Date": "2015-07-10T00:00:00", "IndexCode": "BASIC-IND", "Previous": 417.883, "Highest": 421.071, "Lowest": 416.986, "Close": 416.986, "NumberOfStock": 64.0, "Change": -0.897, "Volume": 883880858.0, "Value": 408903625720.0, "Frequency": 16146.0, "MarketCapital": 292810008820611.0}, {"No": 19, "IndexSummaryID": 69632, "Date": "2015-07-10T00:00:00", "IndexCode": "MISC-IND", "Previous": 1165.724, "Highest": 1176.874, "Lowest": 1152.466, "Close": 1168.668, "NumberOfStock": 42.0, "Change": 2.944, "Volume": 1145915900.0, "Value": 628068370800.0, "Frequency": 36361.0, "MarketCapital": 334300568449620.0}, {"No": 20, "IndexSummaryID": 69633, "Date": "2015-07-10T00:00:00", "IndexCode": "CONSUMER", "Previous": 2157.108, "Highest": 2175.227, "Lowest": 2163.427, "Close": 2169.15, "NumberOfStock": 36.0, "Change": 12.042, "Volume": 73276900.0, "Value": 211256177300.0, "Frequency": 13507.0, "MarketCapital": 1034765189706940.0}, {"No": 21, "IndexSummaryID": 69634, "Date": "2015-07-10T00:00:00", "IndexCode": "PROPERTY", "Previous": 514.755, "Highest": 523.752, "Lowest": 516.583, "Close": 521.868, "NumberOfStock": 57.0, "Change": 7.113, "Volume": 1000936428.0, "Value": 779621787910.0, "Frequency": 44403.0, "MarketCapital": 397449425816060.0}, {"No": 22, "IndexSummaryID": 69635, "Date": "2015-07-10T00:00:00", "IndexCode": "INFRASTRUC", "Previous": 1011.722, "Highest": 1019.001, "Lowest": 1005.692, "Close": 1005.692, "NumberOfStock": 53.0, "Change": -6.03, "Volume": 253130942.0, "Value": 422904942480.0, "Frequency": 18190.0, "MarketCapital": 649067232886458.0}, {"No": 23, "IndexSummaryID": 69636, "Date": "2015-07-10T00:00:00", "IndexCode": "FINANCE", "Previous": 691.741, "Highest": 700.552, "Lowest": 693.648, "Close": 697.009, "NumberOfStock": 85.0, "Change": 5.268, "Volume": 246577275.0, "Value": 835140100172.0, "Frequency": 19965.0, "MarketCapital": 1253520220184060.0}, {"No": 24, "IndexSummaryID": 69637, "Date": "2015-07-10T00:00:00", "IndexCode": "TRADE", "Previous": 900.122, "Highest": 907.91, "Lowest": 900.355, "Close": 904.649, "NumberOfStock": 115.0, "Change": 4.527, "Volume": 608850573.0, "Value": 627618214500.0, "Frequency": 30459.0, "MarketCapital": 658380632878732.0}, {"No": 25, "IndexSummaryID": 69638, "Date": "2015-07-10T00:00:00", "IndexCode": "MANUFACTUR", "Previous": 1211.999, "Highest": 1221.264, "Lowest": 1211.598, "Close": 1215.777, "NumberOfStock": 142.0, "Change": 3.778, "Volume": 2103073658.0, "Value": 1248228173820.0, "Frequency": 66014.0, "MarketCapital": 1661875766977180.0}]