[{"No": 1, "IndexSummaryID": 113993, "Date": "2018-11-22T00:00:00", "IndexCode": "COMPOSITE", "Previous": 5948.052, "Highest": 5997.637, "Lowest": 5936.661, "Close": 5990.81, "NumberOfStock": 616.0, "Change": 42.758, "Volume": 13052946225.0, "Value": 8469736128873.0, "Frequency": 436011.0, "MarketCapital": 6776741379266910.0}, {"No": 2, "IndexSummaryID": 114004, "Date": "2018-11-22T00:00:00", "IndexCode": "LQ45", "Previous": 945.331, "Highest": 957.529, "Lowest": 942.49, "Close": 956.633, "NumberOfStock": 45.0, "Change": 11.302, "Volume": 1910674999.0, "Value": 5274037074184.0, "Frequency": 210437.0, "MarketCapital": 4343160411979880.0}, {"No": 3, "IndexSummaryID": 114013, "Date": "2018-11-22T00:00:00", "IndexCode": "IDX30", "Previous": 521.048, "Highest": 528.028, "Lowest": 519.18, "Close": 527.646, "NumberOfStock": 30.0, "Change": 6.598, "Volume": 1262216181.0, "Value": 4602527310894.0, "Frequency": 164384.0, "MarketCapital": 4049716821951780.0}, {"No": 4, "IndexSummaryID": 114021, "Date": "2018-11-22T00:00:00", "IndexCode": "IDXHIDIV20", "Previous": 506.008, "Highest": 511.292, "Lowest": 503.195, "Close": 511.041, "NumberOfStock": 20.0, "Change": 5.033, "Volume": 756564052.0, "Value": 3380650693139.0, "Frequency": 89383.0, "MarketCapital": 3519484261658900.0}, {"No": 5, "IndexSummaryID": 114022, "Date": "2018-11-22T00:00:00", "IndexCode": "IDXBUMN20", "Previous": 377.176, "Highest": 383.908, "Lowest": 376.52, "Close": 383.504, "NumberOfStock": 20.0, "Change": 6.328, "Volume": 929468174.0, "Value": 2578455173879.0, "Frequency": 97466.0, "MarketCapital": 1667089207673480.0}, {"No": 6, "IndexSummaryID": 114023, "Date": "2018-11-22T00:00:00", "IndexCode": "JII70", "Previous": 219.163, "Highest": 220.493, "Lowest": 218.244, "Close": 220.282, "NumberOfStock": 70.0, "Change": 1.119, "Volume": 4166955678.0, "Value": 3572279152810.0, "Frequency": 192125.0, "MarketCapital": 2537550865982180.0}, {"No": 7, "IndexSummaryID": 114012, "Date": "2018-11-22T00:00:00", "IndexCode": "ISSI", "Previous": 176.962, "Highest": 177.647, "Lowest": 176.433, "Close": 177.516, "NumberOfStock": 390.0, "Change": 0.554, "Volume": 5834528053.0, "Value": 4442030983560.0, "Frequency": 301491.0, "MarketCapital": 3546912195634320.0}, {"No": 8, "IndexSummaryID": 114005, "Date": "2018-11-22T00:00:00", "IndexCode": "JII", "Previous": 663.613, "Highest": 668.433, "Lowest": 660.138, "Close": 668.026, "NumberOfStock": 30.0, "Change": 4.413, "Volume": 1118007765.0, "Value": 2838075770955.0, "Frequency": 143517.0, "MarketCapital": 2082390351482700.0}, {"No": 9, "IndexSummaryID": 114020, "Date": "2018-11-22T00:00:00", "IndexCode": "IDXSMC-LIQ", "Previous": 279.962, "Highest": 283.317, "Lowest": 280.323, "Close": 282.903, "NumberOfStock": 47.0, "Change": 2.941, "Volume": 1234622193.0, "Value": 2083718588465.0, "Frequency": 137967.0, "MarketCapital": 849798791335262.0}, {"No": 10, "IndexSummaryID": 114019, "Date": "2018-11-22T00:00:00", "IndexCode": "IDXSMC-COM", "Previous": 243.337, "Highest": 244.493, "Lowest": 243.623, "Close": 243.999, "NumberOfStock": 336.0, "Change": 0.662, "Volume": 10921486298.0, "Value": 4714605155924.0, "Frequency": 248398.0, "MarketCapital": 2396984162087320.0}, {"No": 11, "IndexSummaryID": 114006, "Date": "2018-11-22T00:00:00", "IndexCode": "MBX", "Previous": 1672.418, "Highest": 1688.919, "Lowest": 1668.784, "Close": 1686.462, "NumberOfStock": 316.0, "Change": 14.044, "Volume": 5341734592.0, "Value": 6877004412835.0, "Frequency": 338622.0, "MarketCapital": 5980235776831150.0}, {"No": 12, "IndexSummaryID": 114007, "Date": "2018-11-22T00:00:00", "IndexCode": "DBX", "Previous": 1000.839, "Highest": 1006.105, "Lowest": 997.171, "Close": 999.058, "NumberOfStock": 300.0, "Change": -1.781, "Volume": 7711211633.0, "Value": 1592731716038.0, "Frequency": 97389.0, "MarketCapital": 796505602435761.0}, {"No": 13, "IndexSummaryID": 114008, "Date": "2018-11-22T00:00:00", "IndexCode": "KOMPAS100", "Previous": 1205.593, "Highest": 1219.656, "Lowest": 1202.527, "Close": 1218.027, "NumberOfStock": 100.0, "Change": 12.434, "Volume": 6925396512.0, "Value": 6901346778529.0, "Frequency": 298656.0, "MarketCapital": 5123707601761300.0}, {"No": 14, "IndexSummaryID": 114014, "Date": "2018-11-22T00:00:00", "IndexCode": "INFOBANK15", "Previous": 871.921, "Highest": 887.718, "Lowest": 870.321, "Close": 886.402, "NumberOfStock": 15.0, "Change": 14.481, "Volume": 391739081.0, "Value": 1978142096119.0, "Frequency": 40412.0, "MarketCapital": 1747078173306360.0}, {"No": 15, "IndexSummaryID": 114009, "Date": "2018-11-22T00:00:00", "IndexCode": "BISNIS-27", "Previous": 533.974, "Highest": 540.681, "Lowest": 531.823, "Close": 540.088, "NumberOfStock": 27.0, "Change": 6.114, "Volume": 897084065.0, "Value": 4221116960414.0, "Frequency": 132556.0, "MarketCapital": 3842571797837540.0}, {"No": 16, "IndexSummaryID": 114017, "Date": "2018-11-22T00:00:00", "IndexCode": "Investor33", "Previous": 433.999, "Highest": 439.261, "Lowest": 432.117, "Close": 439.023, "NumberOfStock": 33.0, "Change": 5.024, "Volume": 1204083446.0, "Value": 4343429255104.0, "Frequency": 144794.0, "MarketCapital": 3616343342000780.0}, {"No": 17, "IndexSummaryID": 114011, "Date": "2018-11-22T00:00:00", "IndexCode": "SRI-KEHATI", "Previous": 368.171, "Highest": 373.031, "Lowest": 366.423, "Close": 373.031, "NumberOfStock": 25.0, "Change": 4.86, "Volume": 809772750.0, "Value": 3456481786754.0, "Frequency": 107255.0, "MarketCapital": 3202140314632850.0}, {"No": 18, "IndexSummaryID": 114015, "Date": "2018-11-22T00:00:00", "IndexCode": "SMinfra18", "Previous": 309.51, "Highest": 314.807, "Lowest": 308.631, "Close": 314.414, "NumberOfStock": 18.0, "Change": 4.904, "Volume": 760410083.0, "Value": 2566840282199.0, "Frequency": 88856.0, "MarketCapital": 1789069104308910.0}, {"No": 19, "IndexSummaryID": 114016, "Date": "2018-11-22T00:00:00", "IndexCode": "MNC36", "Previous": 342.83, "Highest": 346.441, "Lowest": 341.616, "Close": 346.441, "NumberOfStock": 36.0, "Change": 3.611, "Volume": 1203067734.0, "Value": 4421709315734.0, "Frequency": 151725.0, "MarketCapital": 3781402621150720.0}, {"No": 20, "IndexSummaryID": 114018, "Date": "2018-11-22T00:00:00", "IndexCode": "I-GRADE", "Previous": 155.067, "Highest": 157.555, "Lowest": 154.624, "Close": 157.555, "NumberOfStock": 30.0, "Change": 2.488, "Volume": 1178158022.0, "Value": 3180689992494.0, "Frequency": 107923.0, "MarketCapital": 2511280678876410.0}, {"No": 21, "IndexSummaryID": 114010, "Date": "2018-11-22T00:00:00", "IndexCode": "PEFINDO25", "Previous": 311.314, "Highest": 313.221, "Lowest": 310.248, "Close": 312.043, "NumberOfStock": 25.0, "Change": 0.729, "Volume": 501542100.0, "Value": 583062655650.0, "Frequency": 17882.0, "MarketCapital": 152769124309975.0}, {"No": 22, "IndexSummaryID": 113994, "Date": "2018-11-22T00:00:00", "IndexCode": "AGRI", "Previous": 1420.064, "Highest": 1438.758, "Lowest": 1420.064, "Close": 1435.061, "NumberOfStock": 20.0, "Change": 14.997, "Volume": 190840200.0, "Value": 178138465400.0, "Frequency": 11058.0, "MarketCapital": 92272701404524.0}, {"No": 23, "IndexSummaryID": 113995, "Date": "2018-11-22T00:00:00", "IndexCode": "MINING", "Previous": 1752.232, "Highest": 1766.865, "Lowest": 1718.62, "Close": 1724.607, "NumberOfStock": 47.0, "Change": -27.625, "Volume": 986169910.0, "Value": 860434125060.0, "Frequency": 63321.0, "MarketCapital": 388501621409220.0}, {"No": 24, "IndexSummaryID": 113996, "Date": "2018-11-22T00:00:00", "IndexCode": "BASIC-IND", "Previous": 794.852, "Highest": 810.699, "Lowest": 793.203, "Close": 804.853, "NumberOfStock": 71.0, "Change": 10.001, "Volume": 528755581.0, "Value": 820067003725.0, "Frequency": 45455.0, "MarketCapital": 627766169592679.0}, {"No": 25, "IndexSummaryID": 113997, "Date": "2018-11-22T00:00:00", "IndexCode": "MISC-IND", "Previous": 1405.848, "Highest": 1408.15, "Lowest": 1378.511, "Close": 1404.043, "NumberOfStock": 45.0, "Change": -1.805, "Volume": 98515100.0, "Value": 278292465000.0, "Frequency": 12476.0, "MarketCapital": 415850907267845.0}, {"No": 26, "IndexSummaryID": 113998, "Date": "2018-11-22T00:00:00", "IndexCode": "CONSUMER", "Previous": 2338.754, "Highest": 2371.74, "Lowest": 2335.968, "Close": 2361.534, "NumberOfStock": 49.0, "Change": 22.78, "Volume": 788204064.0, "Value": 719707610790.0, "Frequency": 39069.0, "MarketCapital": 1336856786122250.0}, {"No": 27, "IndexSummaryID": 113999, "Date": "2018-11-22T00:00:00", "IndexCode": "PROPERTY", "Previous": 427.067, "Highest": 434.229, "Lowest": 427.908, "Close": 433.411, "NumberOfStock": 72.0, "Change": 6.344, "Volume": 3248358824.0, "Value": 1049140518750.0, "Frequency": 74414.0, "MarketCapital": 374263902158551.0}, {"No": 28, "IndexSummaryID": 114000, "Date": "2018-11-22T00:00:00", "IndexCode": "INFRASTRUC", "Previous": 1070.304, "Highest": 1076.34, "Lowest": 1064.049, "Close": 1071.281, "NumberOfStock": 71.0, "Change": 0.977, "Volume": 1510758010.0, "Value": 725862487520.0, "Frequency": 51803.0, "MarketCapital": 733130037078071.0}, {"No": 29, "IndexSummaryID": 114001, "Date": "2018-11-22T00:00:00", "IndexCode": "FINANCE", "Previous": 1128.672, "Highest": 1145.658, "Lowest": 1126.971, "Close": 1143.884, "NumberOfStock": 91.0, "Change": 15.212, "Volume": 838790615.0, "Value": 2185439584170.0, "Frequency": 50476.0, "MarketCapital": 2121731237184500.0}, {"No": 30, "IndexSummaryID": 114002, "Date": "2018-11-22T00:00:00", "IndexCode": "TRADE", "Previous": 795.747, "Highest": 798.137, "Lowest": 792.983, "Close": 794.75, "NumberOfStock": 150.0, "Change": -0.997, "Volume": 4862553921.0, "Value": 1652653868458.0, "Frequency": 87939.0, "MarketCapital": 686368017049273.0}, {"No": 31, "IndexSummaryID": 114003, "Date": "2018-11-22T00:00:00", "IndexCode": "MANUFACTUR", "Previous": 1507.139, "Highest": 1524.871, "Lowest": 1501.415, "Close": 1520.016, "NumberOfStock": 165.0, "Change": 12.877, "Volume": 1415474745.0, "Value": 1818067079515.0, "Frequency": 97000.0, "MarketCapital": 2380473862982770.0}]