[{"No": 1, "IndexSummaryID": 86328, "Date": "2016-11-09T00:00:00", "IndexCode": "COMPOSITE", "Previous": 5470.681, "Highest": 5491.701, "Lowest": 5345.128, "Close": 5414.321, "NumberOfStock": 538.0, "Change": -56.36, "Volume": 12848215421.0, "Value": 9600627896215.0, "Frequency": 358715.0, "MarketCapital": 5857335587785340.0}, {"No": 2, "IndexSummaryID": 86339, "Date": "2016-11-09T00:00:00", "IndexCode": "LQ45", "Previous": 934.851, "Highest": 939.286, "Lowest": 909.376, "Close": 921.449, "NumberOfStock": 45.0, "Change": -13.402, "Volume": 4388091789.0, "Value": 5890423022678.0, "Frequency": 166354.0, "MarketCapital": 3940261136719710.0}, {"No": 3, "IndexSummaryID": 86348, "Date": "2016-11-09T00:00:00", "IndexCode": "IDX30", "Previous": 505.301, "Highest": 507.756, "Lowest": 491.497, "Close": 497.745, "NumberOfStock": 30.0, "Change": -7.556, "Volume": 1310896136.0, "Value": 4872063676898.0, "Frequency": 120939.0, "MarketCapital": 3682777426527750.0}, {"No": 4, "IndexSummaryID": 86347, "Date": "2016-11-09T00:00:00", "IndexCode": "ISSI", "Previous": 180.192, "Highest": 180.726, "Lowest": 175.796, "Close": 178.223, "NumberOfStock": 311.0, "Change": -1.969, "Volume": 3924655769.0, "Value": 6049521804314.0, "Frequency": 219458.0, "MarketCapital": 3273046230982370.0}, {"No": 5, "IndexSummaryID": 86340, "Date": "2016-11-09T00:00:00", "IndexCode": "JII", "Previous": 740.903, "Highest": 743.158, "Lowest": 719.802, "Close": 730.088, "NumberOfStock": 30.0, "Change": -10.815, "Volume": 1207735485.0, "Value": 3630975103253.0, "Frequency": 106136.0, "MarketCapital": 2159723140305160.0}, {"No": 6, "IndexSummaryID": 86341, "Date": "2016-11-09T00:00:00", "IndexCode": "MBX", "Previous": 1562.396, "Highest": 1568.742, "Lowest": 1524.022, "Close": 1544.286, "NumberOfStock": 281.0, "Change": -18.11, "Volume": 4130861711.0, "Value": 6976591650709.0, "Frequency": 265964.0, "MarketCapital": 5220945859041730.0}, {"No": 7, "IndexSummaryID": 86342, "Date": "2016-11-09T00:00:00", "IndexCode": "DBX", "Previous": 813.322, "Highest": 815.221, "Lowest": 804.502, "Close": 813.599, "NumberOfStock": 257.0, "Change": 0.277, "Volume": 8717353710.0, "Value": 2624036245506.0, "Frequency": 92751.0, "MarketCapital": 636389728743605.0}, {"No": 8, "IndexSummaryID": 86343, "Date": "2016-11-09T00:00:00", "IndexCode": "KOMPAS100", "Previous": 1172.683, "Highest": 1177.958, "Lowest": 1140.551, "Close": 1157.242, "NumberOfStock": 100.0, "Change": -15.441, "Volume": 8966525551.0, "Value": 7798246400079.0, "Frequency": 275202.0, "MarketCapital": 4502747543687260.0}, {"No": 9, "IndexSummaryID": 86349, "Date": "2016-11-09T00:00:00", "IndexCode": "INFOBANK15", "Previous": 623.0, "Highest": 628.981, "Lowest": 607.842, "Close": 612.43, "NumberOfStock": 15.0, "Change": -10.57, "Volume": 266910494.0, "Value": 1478276281795.0, "Frequency": 26842.0, "MarketCapital": 1203951686285150.0}, {"No": 10, "IndexSummaryID": 86344, "Date": "2016-11-09T00:00:00", "IndexCode": "BISNIS-27", "Previous": 486.469, "Highest": 489.028, "Lowest": 472.31, "Close": 477.503, "NumberOfStock": 27.0, "Change": -8.966, "Volume": 1169052879.0, "Value": 4370992432540.0, "Frequency": 106055.0, "MarketCapital": 2869592510436380.0}, {"No": 11, "IndexSummaryID": 86352, "Date": "2016-11-09T00:00:00", "IndexCode": "Investor33", "Previous": 390.316, "Highest": 392.122, "Lowest": 380.399, "Close": 384.091, "NumberOfStock": 33.0, "Change": -6.225, "Volume": 1383139448.0, "Value": 4194383090963.0, "Frequency": 99339.0, "MarketCapital": 3131931845880850.0}, {"No": 12, "IndexSummaryID": 86346, "Date": "2016-11-09T00:00:00", "IndexCode": "SRI-KEHATI", "Previous": 326.332, "Highest": 327.786, "Lowest": 317.789, "Close": 320.716, "NumberOfStock": 25.0, "Change": -5.616, "Volume": 723241145.0, "Value": 3729721983840.0, "Frequency": 78078.0, "MarketCapital": 2738028124061070.0}, {"No": 13, "IndexSummaryID": 86350, "Date": "2016-11-09T00:00:00", "IndexCode": "SMinfra18", "Previous": 357.962, "Highest": 359.488, "Lowest": 346.645, "Close": 350.456, "NumberOfStock": 18.0, "Change": -7.506, "Volume": 462169570.0, "Value": 1530373387735.0, "Frequency": 41217.0, "MarketCapital": 906180577622245.0}, {"No": 14, "IndexSummaryID": 86351, "Date": "2016-11-09T00:00:00", "IndexCode": "MNC36", "Previous": 311.445, "Highest": 312.697, "Lowest": 303.297, "Close": 306.059, "NumberOfStock": 36.0, "Change": -5.386, "Volume": 3047780694.0, "Value": 3113519495995.0, "Frequency": 88736.0, "MarketCapital": 2290528818617910.0}, {"No": 15, "IndexSummaryID": 86345, "Date": "2016-11-09T00:00:00", "IndexCode": "PEFINDO25", "Previous": 388.43, "Highest": 392.31, "Lowest": 381.694, "Close": 388.697, "NumberOfStock": 25.0, "Change": 0.267, "Volume": 258619187.0, "Value": 560043005375.0, "Frequency": 25289.0, "MarketCapital": 246396752059944.0}, {"No": 16, "IndexSummaryID": 86329, "Date": "2016-11-09T00:00:00", "IndexCode": "AGRI", "Previous": 1770.387, "Highest": 1773.244, "Lowest": 1735.113, "Close": 1756.268, "NumberOfStock": 21.0, "Change": -14.119, "Volume": 311238700.0, "Value": 265008624200.0, "Frequency": 14454.0, "MarketCapital": 129257525247990.0}, {"No": 17, "IndexSummaryID": 86330, "Date": "2016-11-09T00:00:00", "IndexCode": "MINING", "Previous": 1390.752, "Highest": 1395.734, "Lowest": 1337.003, "Close": 1380.67, "NumberOfStock": 43.0, "Change": -10.082, "Volume": 3747118923.0, "Value": 1824125198300.0, "Frequency": 83168.0, "MarketCapital": 284904087766873.0}, {"No": 18, "IndexSummaryID": 86331, "Date": "2016-11-09T00:00:00", "IndexCode": "BASIC-IND", "Previous": 544.249, "Highest": 547.438, "Lowest": 529.287, "Close": 538.076, "NumberOfStock": 66.0, "Change": -6.173, "Volume": 809613295.0, "Value": 823098492000.0, "Frequency": 34195.0, "MarketCapital": 397334703709722.0}, {"No": 19, "IndexSummaryID": 86332, "Date": "2016-11-09T00:00:00", "IndexCode": "MISC-IND", "Previous": 1390.86, "Highest": 1394.513, "Lowest": 1349.641, "Close": 1374.197, "NumberOfStock": 42.0, "Change": -16.663, "Volume": 550893883.0, "Value": 726846069850.0, "Frequency": 23498.0, "MarketCapital": 394741583997649.0}, {"No": 20, "IndexSummaryID": 86333, "Date": "2016-11-09T00:00:00", "IndexCode": "CONSUMER", "Previous": 2503.115, "Highest": 2514.346, "Lowest": 2445.259, "Close": 2489.631, "NumberOfStock": 39.0, "Change": -13.484, "Volume": 118198946.0, "Value": 522779685215.0, "Frequency": 23626.0, "MarketCapital": 1376715950119190.0}, {"No": 21, "IndexSummaryID": 86334, "Date": "2016-11-09T00:00:00", "IndexCode": "PROPERTY", "Previous": 554.774, "Highest": 556.567, "Lowest": 540.938, "Close": 549.249, "NumberOfStock": 63.0, "Change": -5.525, "Volume": 3550253696.0, "Value": 1162912199956.0, "Frequency": 49933.0, "MarketCapital": 441459996921908.0}, {"No": 22, "IndexSummaryID": 86335, "Date": "2016-11-09T00:00:00", "IndexCode": "INFRASTRUC", "Previous": 1107.976, "Highest": 1111.197, "Lowest": 1076.866, "Close": 1083.26, "NumberOfStock": 56.0, "Change": -24.716, "Volume": 383528568.0, "Value": 900867616810.0, "Frequency": 28339.0, "MarketCapital": 738205910895583.0}, {"No": 23, "IndexSummaryID": 86336, "Date": "2016-11-09T00:00:00", "IndexCode": "FINANCE", "Previous": 821.182, "Highest": 828.184, "Lowest": 803.218, "Close": 808.693, "NumberOfStock": 88.0, "Change": -12.489, "Volume": 1156816642.0, "Value": 1713533817601.0, "Frequency": 42867.0, "MarketCapital": 1472233139001020.0}, {"No": 24, "IndexSummaryID": 86337, "Date": "2016-11-09T00:00:00", "IndexCode": "TRADE", "Previous": 862.952, "Highest": 869.61, "Lowest": 847.693, "Close": 866.875, "NumberOfStock": 120.0, "Change": 3.923, "Volume": 2220552768.0, "Value": 1661456192283.0, "Frequency": 58635.0, "MarketCapital": 622482690125403.0}, {"No": 25, "IndexSummaryID": 86338, "Date": "2016-11-09T00:00:00", "IndexCode": "MANUFACTUR", "Previous": 1440.643, "Highest": 1446.607, "Lowest": 1406.484, "Close": 1429.568, "NumberOfStock": 147.0, "Change": -11.075, "Volume": 1478706124.0, "Value": 2072724247065.0, "Frequency": 81319.0, "MarketCapital": 2168792237826560.0}]