[{"No": 1, "IndexSummaryID": 129520, "Date": "2020-06-03T00:00:00", "IndexCode": "COMPOSITE", "Previous": 4847.507, "Highest": 4960.071, "Lowest": 4847.522, "Close": 4941.006, "NumberOfStock": 692.0, "Change": 93.499, "Volume": 11130031295.0, "Value": 12857287779331.0, "Frequency": 879967.0, "MarketCapital": 5713182460052770.0}, {"No": 2, "IndexSummaryID": 129531, "Date": "2020-06-03T00:00:00", "IndexCode": "LQ45", "Previous": 749.517, "Highest": 772.066, "Lowest": 748.192, "Close": 770.664, "NumberOfStock": 45.0, "Change": 21.147, "Volume": 5046996120.0, "Value": 10986896409148.0, "Frequency": 550291.0, "MarketCapital": 3651661628731100.0}, {"No": 3, "IndexSummaryID": 129540, "Date": "2020-06-03T00:00:00", "IndexCode": "IDX30", "Previous": 411.55, "Highest": 423.673, "Lowest": 410.105, "Close": 422.072, "NumberOfStock": 30.0, "Change": 10.522, "Volume": 3783810020.0, "Value": 9616958307380.0, "Frequency": 439747.0, "MarketCapital": 3380496678918120.0}, {"No": 4, "IndexSummaryID": 129551, "Date": "2020-06-03T00:00:00", "IndexCode": "IDX80", "Previous": 105.856, "Highest": 108.814, "Lowest": 105.73, "Close": 108.649, "NumberOfStock": 80.0, "Change": 2.793, "Volume": 6597412986.0, "Value": 11791688278602.0, "Frequency": 655629.0, "MarketCapital": 4129022472060570.0}, {"No": 5, "IndexSummaryID": 129552, "Date": "2020-06-03T00:00:00", "IndexCode": "IDXV30", "Previous": 88.43, "Highest": 93.301, "Lowest": 88.496, "Close": 93.15, "NumberOfStock": 30.0, "Change": 4.72, "Volume": 3378979696.0, "Value": 3447111933185.0, "Frequency": 242039.0, "MarketCapital": 431870187410114.0}, {"No": 6, "IndexSummaryID": 129553, "Date": "2020-06-03T00:00:00", "IndexCode": "IDXG30", "Previous": 112.99, "Highest": 116.041, "Lowest": 112.708, "Close": 115.65, "NumberOfStock": 30.0, "Change": 2.66, "Volume": 2734534754.0, "Value": 7323468164638.0, "Frequency": 338899.0, "MarketCapital": 2536605852949080.0}, {"No": 7, "IndexSummaryID": 129548, "Date": "2020-06-03T00:00:00", "IndexCode": "IDXHIDIV20", "Previous": 370.238, "Highest": 381.159, "Lowest": 368.576, "Close": 379.841, "NumberOfStock": 20.0, "Change": 9.603, "Volume": 2287177031.0, "Value": 7789669436907.0, "Frequency": 301311.0, "MarketCapital": 3013496070569240.0}, {"No": 8, "IndexSummaryID": 129549, "Date": "2020-06-03T00:00:00", "IndexCode": "IDXBUMN20", "Previous": 265.071, "Highest": 275.341, "Lowest": 262.266, "Close": 271.21, "NumberOfStock": 20.0, "Change": 6.139, "Volume": 3099385116.0, "Value": 5386126266422.0, "Frequency": 264409.0, "MarketCapital": 1210413054289980.0}, {"No": 9, "IndexSummaryID": 129550, "Date": "2020-06-03T00:00:00", "IndexCode": "JII70", "Previous": 180.465, "Highest": 184.311, "Lowest": 180.468, "Close": 183.831, "NumberOfStock": 70.0, "Change": 3.366, "Volume": 5194759504.0, "Value": 5591082924299.0, "Frequency": 417969.0, "MarketCapital": 2206766995101270.0}, {"No": 10, "IndexSummaryID": 129539, "Date": "2020-06-03T00:00:00", "IndexCode": "ISSI", "Previous": 146.68, "Highest": 149.149, "Lowest": 146.681, "Close": 148.648, "NumberOfStock": 445.0, "Change": 1.968, "Volume": 7469439510.0, "Value": 6160239538797.0, "Frequency": 552845.0, "MarketCapital": 2975226890159980.0}, {"No": 11, "IndexSummaryID": 129532, "Date": "2020-06-03T00:00:00", "IndexCode": "JII", "Previous": 543.194, "Highest": 555.665, "Lowest": 543.982, "Close": 553.829, "NumberOfStock": 30.0, "Change": 10.635, "Volume": 2688662046.0, "Value": 4780172089149.0, "Frequency": 290220.0, "MarketCapital": 1839488132875720.0}, {"No": 12, "IndexSummaryID": 129547, "Date": "2020-06-03T00:00:00", "IndexCode": "IDXSMC-LIQ", "Previous": 222.087, "Highest": 229.741, "Lowest": 222.166, "Close": 229.362, "NumberOfStock": 52.0, "Change": 7.275, "Volume": 4715551947.0, "Value": 4323977194704.0, "Frequency": 364515.0, "MarketCapital": 766130492653043.0}, {"No": 13, "IndexSummaryID": 129546, "Date": "2020-06-03T00:00:00", "IndexCode": "IDXSMC-COM", "Previous": 195.814, "Highest": 199.18, "Lowest": 195.815, "Close": 199.035, "NumberOfStock": 357.0, "Change": 3.221, "Volume": 8677900217.0, "Value": 5370995817082.0, "Frequency": 552894.0, "MarketCapital": 2099885425008910.0}, {"No": 14, "IndexSummaryID": 129533, "Date": "2020-06-03T00:00:00", "IndexCode": "MBX", "Previous": 1344.256, "Highest": 1379.213, "Lowest": 1344.926, "Close": 1373.7, "NumberOfStock": 340.0, "Change": 29.444, "Volume": 9730761281.0, "Value": 12270288954997.0, "Frequency": 790230.0, "MarketCapital": 5003126006861750.0}, {"No": 15, "IndexSummaryID": 129534, "Date": "2020-06-03T00:00:00", "IndexCode": "DBX", "Previous": 902.066, "Highest": 906.855, "Lowest": 899.862, "Close": 903.177, "NumberOfStock": 352.0, "Change": 1.111, "Volume": 1399270014.0, "Value": 586998824334.0, "Frequency": 89737.0, "MarketCapital": 710056453191014.0}, {"No": 16, "IndexSummaryID": 129535, "Date": "2020-06-03T00:00:00", "IndexCode": "KOMPAS100", "Previous": 969.136, "Highest": 997.118, "Lowest": 969.713, "Close": 994.529, "NumberOfStock": 100.0, "Change": 25.393, "Volume": 7486245619.0, "Value": 12041393073400.0, "Frequency": 690972.0, "MarketCapital": 4209205054701810.0}, {"No": 17, "IndexSummaryID": 129541, "Date": "2020-06-03T00:00:00", "IndexCode": "INFOBANK15", "Previous": 743.236, "Highest": 777.103, "Lowest": 741.629, "Close": 772.027, "NumberOfStock": 15.0, "Change": 28.791, "Volume": 1542131034.0, "Value": 5368015145645.0, "Frequency": 194412.0, "MarketCapital": 1592997484298500.0}, {"No": 18, "IndexSummaryID": 129536, "Date": "2020-06-03T00:00:00", "IndexCode": "BISNIS-27", "Previous": 427.568, "Highest": 440.821, "Lowest": 427.906, "Close": 440.003, "NumberOfStock": 27.0, "Change": 12.435, "Volume": 2746133034.0, "Value": 8645414302029.0, "Frequency": 360873.0, "MarketCapital": 3176385484575490.0}, {"No": 19, "IndexSummaryID": 129544, "Date": "2020-06-03T00:00:00", "IndexCode": "Investor33", "Previous": 352.269, "Highest": 364.32, "Lowest": 352.569, "Close": 363.628, "NumberOfStock": 33.0, "Change": 11.359, "Volume": 3822246299.0, "Value": 9059947202240.0, "Frequency": 390546.0, "MarketCapital": 2952702067769840.0}, {"No": 20, "IndexSummaryID": 129538, "Date": "2020-06-03T00:00:00", "IndexCode": "SRI-KEHATI", "Previous": 298.357, "Highest": 309.121, "Lowest": 298.643, "Close": 308.314, "NumberOfStock": 25.0, "Change": 9.957, "Volume": 3627743448.0, "Value": 8521634250196.0, "Frequency": 360638.0, "MarketCapital": 2636021099160780.0}, {"No": 21, "IndexSummaryID": 129542, "Date": "2020-06-03T00:00:00", "IndexCode": "SMinfra18", "Previous": 232.541, "Highest": 238.333, "Lowest": 231.469, "Close": 237.564, "NumberOfStock": 18.0, "Change": 5.023, "Volume": 2254346216.0, "Value": 5009918956307.0, "Frequency": 231098.0, "MarketCapital": 1385868986736710.0}, {"No": 22, "IndexSummaryID": 129543, "Date": "2020-06-03T00:00:00", "IndexCode": "MNC36", "Previous": 274.383, "Highest": 283.325, "Lowest": 274.584, "Close": 282.491, "NumberOfStock": 36.0, "Change": 8.108, "Volume": 4251561918.0, "Value": 9495797420629.0, "Frequency": 440468.0, "MarketCapital": 3444366511580540.0}, {"No": 23, "IndexSummaryID": 129545, "Date": "2020-06-03T00:00:00", "IndexCode": "I-GRADE", "Previous": 132.452, "Highest": 136.788, "Lowest": 131.849, "Close": 135.504, "NumberOfStock": 30.0, "Change": 3.052, "Volume": 2949712348.0, "Value": 7177016703677.0, "Frequency": 302390.0, "MarketCapital": 2377883325057770.0}, {"No": 24, "IndexSummaryID": 129537, "Date": "2020-06-03T00:00:00", "IndexCode": "PEFINDO25", "Previous": 245.382, "Highest": 249.542, "Lowest": 242.875, "Close": 245.475, "NumberOfStock": 25.0, "Change": 0.093, "Volume": 1110512933.0, "Value": 439006389564.0, "Frequency": 71484.0, "MarketCapital": 153163531427977.0}, {"No": 25, "IndexSummaryID": 129521, "Date": "2020-06-03T00:00:00", "IndexCode": "AGRI", "Previous": 966.684, "Highest": 1000.377, "Lowest": 967.761, "Close": 997.725, "NumberOfStock": 22.0, "Change": 31.041, "Volume": 132844882.0, "Value": 92649941160.0, "Frequency": 12897.0, "MarketCapital": 63200236345645.0}, {"No": 26, "IndexSummaryID": 129522, "Date": "2020-06-03T00:00:00", "IndexCode": "MINING", "Previous": 1270.446, "Highest": 1285.263, "Lowest": 1263.49, "Close": 1282.05, "NumberOfStock": 49.0, "Change": 11.604, "Volume": 1259414635.0, "Value": 772554979845.0, "Frequency": 74664.0, "MarketCapital": 298364733351765.0}, {"No": 27, "IndexSummaryID": 129523, "Date": "2020-06-03T00:00:00", "IndexCode": "BASIC-IND", "Previous": 759.541, "Highest": 771.695, "Lowest": 759.836, "Close": 767.744, "NumberOfStock": 78.0, "Change": 8.203, "Volume": 966082705.0, "Value": 1188899566458.0, "Frequency": 110862.0, "MarketCapital": 609040184488783.0}, {"No": 28, "IndexSummaryID": 129524, "Date": "2020-06-03T00:00:00", "IndexCode": "MISC-IND", "Previous": 854.205, "Highest": 884.647, "Lowest": 847.018, "Close": 876.889, "NumberOfStock": 52.0, "Change": 22.684, "Volume": 239370452.0, "Value": 449366696376.0, "Frequency": 24342.0, "MarketCapital": 266331366569427.0}, {"No": 29, "IndexSummaryID": 129525, "Date": "2020-06-03T00:00:00", "IndexCode": "CONSUMER", "Previous": 1820.498, "Highest": 1865.936, "Lowest": 1820.498, "Close": 1838.287, "NumberOfStock": 58.0, "Change": 17.789, "Volume": 361662800.0, "Value": 1046735208918.0, "Frequency": 76106.0, "MarketCapital": 1054663525770410.0}, {"No": 30, "IndexSummaryID": 129526, "Date": "2020-06-03T00:00:00", "IndexCode": "PROPERTY", "Previous": 326.467, "Highest": 336.785, "Lowest": 326.614, "Close": 333.01, "NumberOfStock": 90.0, "Change": 6.543, "Volume": 2617934630.0, "Value": 865826135190.0, "Frequency": 103942.0, "MarketCapital": 306782371351037.0}, {"No": 31, "IndexSummaryID": 129527, "Date": "2020-06-03T00:00:00", "IndexCode": "INFRASTRUC", "Previous": 883.534, "Highest": 899.989, "Lowest": 882.593, "Close": 899.989, "NumberOfStock": 78.0, "Change": 16.455, "Volume": 1513865735.0, "Value": 1790629698418.0, "Frequency": 134304.0, "MarketCapital": 629869223887894.0}, {"No": 32, "IndexSummaryID": 129528, "Date": "2020-06-03T00:00:00", "IndexCode": "FINANCE", "Previous": 995.519, "Highest": 1033.281, "Lowest": 993.195, "Close": 1027.339, "NumberOfStock": 93.0, "Change": 31.82, "Volume": 2272012063.0, "Value": 5641428720964.0, "Frequency": 230513.0, "MarketCapital": 1932152965510680.0}, {"No": 33, "IndexSummaryID": 129529, "Date": "2020-06-03T00:00:00", "IndexCode": "TRADE", "Previous": 611.583, "Highest": 619.64, "Lowest": 611.512, "Close": 614.307, "NumberOfStock": 172.0, "Change": 2.724, "Volume": 1766843393.0, "Value": 1009196832002.0, "Frequency": 112337.0, "MarketCapital": 552777852777128.0}, {"No": 34, "IndexSummaryID": 129530, "Date": "2020-06-03T00:00:00", "IndexCode": "MANUFACTUR", "Previous": 1197.742, "Highest": 1220.474, "Lowest": 1197.738, "Close": 1212.571, "NumberOfStock": 188.0, "Change": 14.829, "Volume": 1567115957.0, "Value": 2685001471752.0, "Frequency": 211310.0, "MarketCapital": 1930035076828620.0}]