[{"No": 1, "IndexSummaryID": 124284, "Date": "2019-10-22T00:00:00", "IndexCode": "COMPOSITE", "Previous": 6198.987, "Highest": 6229.399, "Lowest": 6178.555, "Close": 6225.497, "NumberOfStock": 659.0, "Change": 26.51, "Volume": 16714070436.0, "Value": 8197666183278.0, "Frequency": 492287.0, "MarketCapital": 7159844320499370.0}, {"No": 2, "IndexSummaryID": 124295, "Date": "2019-10-22T00:00:00", "IndexCode": "LQ45", "Previous": 975.692, "Highest": 982.913, "Lowest": 971.068, "Close": 982.913, "NumberOfStock": 45.0, "Change": 7.221, "Volume": 1104536619.0, "Value": 4034796917563.0, "Frequency": 165486.0, "MarketCapital": 4606116135857740.0}, {"No": 3, "IndexSummaryID": 124304, "Date": "2019-10-22T00:00:00", "IndexCode": "IDX30", "Previous": 531.705, "Highest": 535.765, "Lowest": 528.892, "Close": 535.765, "NumberOfStock": 30.0, "Change": 4.06, "Volume": 816514371.0, "Value": 3442733060243.0, "Frequency": 116621.0, "MarketCapital": 4115834254852250.0}, {"No": 4, "IndexSummaryID": 124315, "Date": "2019-10-22T00:00:00", "IndexCode": "IDX80", "Previous": 139.053, "Highest": 139.833, "Lowest": 138.262, "Close": 139.833, "NumberOfStock": 80.0, "Change": 0.78, "Volume": 2147046495.0, "Value": 4662873781853.0, "Frequency": 209262.0, "MarketCapital": 5148606448632640.0}, {"No": 5, "IndexSummaryID": 124316, "Date": "2019-10-22T00:00:00", "IndexCode": "IDXV30", "Previous": 139.489, "Highest": 140.484, "Lowest": 138.291, "Close": 139.965, "NumberOfStock": 30.0, "Change": 0.476, "Volume": 434547555.0, "Value": 910370713358.0, "Frequency": 61406.0, "MarketCapital": 723467550873266.0}, {"No": 6, "IndexSummaryID": 124317, "Date": "2019-10-22T00:00:00", "IndexCode": "IDXG30", "Previous": 139.048, "Highest": 140.181, "Lowest": 138.447, "Close": 140.181, "NumberOfStock": 30.0, "Change": 1.133, "Volume": 889883375.0, "Value": 2501489036025.0, "Frequency": 80750.0, "MarketCapital": 2985087109017660.0}, {"No": 7, "IndexSummaryID": 124312, "Date": "2019-10-22T00:00:00", "IndexCode": "IDXHIDIV20", "Previous": 484.209, "Highest": 486.791, "Lowest": 479.984, "Close": 485.84, "NumberOfStock": 20.0, "Change": 1.631, "Volume": 512335808.0, "Value": 2804766280930.0, "Frequency": 80122.0, "MarketCapital": 3501006445926030.0}, {"No": 8, "IndexSummaryID": 124313, "Date": "2019-10-22T00:00:00", "IndexCode": "IDXBUMN20", "Previous": 387.256, "Highest": 389.296, "Lowest": 383.893, "Close": 388.344, "NumberOfStock": 20.0, "Change": 1.088, "Volume": 764415944.0, "Value": 1591000434180.0, "Frequency": 54059.0, "MarketCapital": 1716753290380770.0}, {"No": 9, "IndexSummaryID": 124314, "Date": "2019-10-22T00:00:00", "IndexCode": "JII70", "Previous": 232.907, "Highest": 234.854, "Lowest": 232.517, "Close": 234.854, "NumberOfStock": 70.0, "Change": 1.947, "Volume": 2519784126.0, "Value": 2840430006258.0, "Frequency": 183076.0, "MarketCapital": 2825513295113610.0}, {"No": 10, "IndexSummaryID": 124303, "Date": "2019-10-22T00:00:00", "IndexCode": "ISSI", "Previous": 189.552, "Highest": 190.742, "Lowest": 189.347, "Close": 190.742, "NumberOfStock": 413.0, "Change": 1.19, "Volume": 7736704895.0, "Value": 4582708533968.0, "Frequency": 340103.0, "MarketCapital": 3832315435983840.0}, {"No": 11, "IndexSummaryID": 124296, "Date": "2019-10-22T00:00:00", "IndexCode": "JII", "Previous": 683.733, "Highest": 691.27, "Lowest": 682.224, "Close": 691.27, "NumberOfStock": 30.0, "Change": 7.537, "Volume": 634222551.0, "Value": 1944435894125.0, "Frequency": 91448.0, "MarketCapital": 2140753857604960.0}, {"No": 12, "IndexSummaryID": 124311, "Date": "2019-10-22T00:00:00", "IndexCode": "IDXSMC-LIQ", "Previous": 320.464, "Highest": 322.386, "Lowest": 319.078, "Close": 321.18, "NumberOfStock": 56.0, "Change": 0.716, "Volume": 1081091040.0, "Value": 1426033853478.0, "Frequency": 124050.0, "MarketCapital": 996673379212030.0}, {"No": 13, "IndexSummaryID": 124310, "Date": "2019-10-22T00:00:00", "IndexCode": "IDXSMC-COM", "Previous": 267.058, "Highest": 268.136, "Lowest": 266.654, "Close": 267.861, "NumberOfStock": 372.0, "Change": 0.803, "Volume": 14224351374.0, "Value": 4635542499720.0, "Frequency": 318884.0, "MarketCapital": 2849192519811580.0}, {"No": 14, "IndexSummaryID": 124297, "Date": "2019-10-22T00:00:00", "IndexCode": "MBX", "Previous": 1721.167, "Highest": 1730.299, "Lowest": 1714.596, "Close": 1729.005, "NumberOfStock": 333.0, "Change": 7.838, "Volume": 5939185313.0, "Value": 5908766079194.0, "Frequency": 323610.0, "MarketCapital": 6266262939953190.0}, {"No": 15, "IndexSummaryID": 124298, "Date": "2019-10-22T00:00:00", "IndexCode": "DBX", "Previous": 1145.781, "Highest": 1150.248, "Lowest": 1127.136, "Close": 1148.463, "NumberOfStock": 326.0, "Change": 2.682, "Volume": 10774885123.0, "Value": 2288900104084.0, "Frequency": 168677.0, "MarketCapital": 893581380546181.0}, {"No": 16, "IndexSummaryID": 124299, "Date": "2019-10-22T00:00:00", "IndexCode": "KOMPAS100", "Previous": 1245.188, "Highest": 1252.667, "Lowest": 1238.919, "Close": 1250.883, "NumberOfStock": 100.0, "Change": 5.695, "Volume": 2558463669.0, "Value": 4881988105895.0, "Frequency": 234574.0, "MarketCapital": 5285774092735710.0}, {"No": 17, "IndexSummaryID": 124305, "Date": "2019-10-22T00:00:00", "IndexCode": "INFOBANK15", "Previous": 964.312, "Highest": 971.235, "Lowest": 960.349, "Close": 971.235, "NumberOfStock": 15.0, "Change": 6.923, "Volume": 322403143.0, "Value": 1582413858260.0, "Frequency": 35513.0, "MarketCapital": 1997439551839250.0}, {"No": 18, "IndexSummaryID": 124300, "Date": "2019-10-22T00:00:00", "IndexCode": "BISNIS-27", "Previous": 541.41, "Highest": 544.06, "Lowest": 537.953, "Close": 543.502, "NumberOfStock": 27.0, "Change": 2.092, "Volume": 740723253.0, "Value": 3120129654355.0, "Frequency": 96958.0, "MarketCapital": 3820824544753510.0}, {"No": 19, "IndexSummaryID": 124308, "Date": "2019-10-22T00:00:00", "IndexCode": "Investor33", "Previous": 453.512, "Highest": 457.011, "Lowest": 452.01, "Close": 457.011, "NumberOfStock": 33.0, "Change": 3.499, "Volume": 639014114.0, "Value": 2608681652743.0, "Frequency": 91599.0, "MarketCapital": 3348968866418040.0}, {"No": 20, "IndexSummaryID": 124302, "Date": "2019-10-22T00:00:00", "IndexCode": "SRI-KEHATI", "Previous": 387.337, "Highest": 390.052, "Lowest": 385.843, "Close": 390.052, "NumberOfStock": 25.0, "Change": 2.715, "Volume": 505645747.0, "Value": 2586738434050.0, "Frequency": 70545.0, "MarketCapital": 3334529655744890.0}, {"No": 21, "IndexSummaryID": 124306, "Date": "2019-10-22T00:00:00", "IndexCode": "SMinfra18", "Previous": 325.201, "Highest": 328.158, "Lowest": 324.287, "Close": 328.158, "NumberOfStock": 18.0, "Change": 2.957, "Volume": 408597336.0, "Value": 1703920243500.0, "Frequency": 55089.0, "MarketCapital": 1876376738900590.0}, {"No": 22, "IndexSummaryID": 124307, "Date": "2019-10-22T00:00:00", "IndexCode": "MNC36", "Previous": 338.152, "Highest": 339.924, "Lowest": 336.203, "Close": 339.577, "NumberOfStock": 36.0, "Change": 1.425, "Volume": 877693012.0, "Value": 3275428575145.0, "Frequency": 129299.0, "MarketCapital": 3734609350670510.0}, {"No": 23, "IndexSummaryID": 124309, "Date": "2019-10-22T00:00:00", "IndexCode": "I-GRADE", "Previous": 173.905, "Highest": 174.951, "Lowest": 173.24, "Close": 174.951, "NumberOfStock": 30.0, "Change": 1.046, "Volume": 639657623.0, "Value": 2400103518940.0, "Frequency": 77689.0, "MarketCapital": 2947842720628170.0}, {"No": 24, "IndexSummaryID": 124301, "Date": "2019-10-22T00:00:00", "IndexCode": "PEFINDO25", "Previous": 358.768, "Highest": 360.369, "Lowest": 352.815, "Close": 354.738, "NumberOfStock": 25.0, "Change": -4.03, "Volume": 475550800.0, "Value": 418224027400.0, "Frequency": 30012.0, "MarketCapital": 187714396333917.0}, {"No": 25, "IndexSummaryID": 124285, "Date": "2019-10-22T00:00:00", "IndexCode": "AGRI", "Previous": 1335.316, "Highest": 1341.971, "Lowest": 1325.652, "Close": 1332.891, "NumberOfStock": 20.0, "Change": -2.425, "Volume": 130803708.0, "Value": 86841943050.0, "Frequency": 6686.0, "MarketCapital": 81592747735790.0}, {"No": 26, "IndexSummaryID": 124286, "Date": "2019-10-22T00:00:00", "IndexCode": "MINING", "Previous": 1590.926, "Highest": 1594.118, "Lowest": 1580.366, "Close": 1590.141, "NumberOfStock": 48.0, "Change": -0.785, "Volume": 2399301026.0, "Value": 693690117755.0, "Frequency": 35827.0, "MarketCapital": 367376851319147.0}, {"No": 27, "IndexSummaryID": 124287, "Date": "2019-10-22T00:00:00", "IndexCode": "BASIC-IND", "Previous": 907.859, "Highest": 925.305, "Lowest": 900.994, "Close": 925.305, "NumberOfStock": 74.0, "Change": 17.446, "Volume": 422024643.0, "Value": 674910309702.0, "Frequency": 46754.0, "MarketCapital": 731892408972059.0}, {"No": 28, "IndexSummaryID": 124288, "Date": "2019-10-22T00:00:00", "IndexCode": "MISC-IND", "Previous": 1200.44, "Highest": 1207.477, "Lowest": 1176.872, "Close": 1203.327, "NumberOfStock": 50.0, "Change": 2.887, "Volume": 226164859.0, "Value": 317785594222.0, "Frequency": 14136.0, "MarketCapital": 358299324786054.0}, {"No": 29, "IndexSummaryID": 124289, "Date": "2019-10-22T00:00:00", "IndexCode": "CONSUMER", "Previous": 2118.599, "Highest": 2133.841, "Lowest": 2097.437, "Close": 2101.126, "NumberOfStock": 54.0, "Change": -17.473, "Volume": 325056574.0, "Value": 852490483044.0, "Frequency": 39246.0, "MarketCapital": 1195398615223670.0}, {"No": 30, "IndexSummaryID": 124290, "Date": "2019-10-22T00:00:00", "IndexCode": "PROPERTY", "Previous": 507.495, "Highest": 511.512, "Lowest": 506.777, "Close": 509.572, "NumberOfStock": 82.0, "Change": 2.077, "Volume": 3056040902.0, "Value": 729270442620.0, "Frequency": 40420.0, "MarketCapital": 476002156506404.0}, {"No": 31, "IndexSummaryID": 124291, "Date": "2019-10-22T00:00:00", "IndexCode": "INFRASTRUC", "Previous": 1208.713, "Highest": 1219.679, "Lowest": 1207.267, "Close": 1214.902, "NumberOfStock": 75.0, "Change": 6.189, "Volume": 750239942.0, "Value": 1044564002100.0, "Frequency": 67304.0, "MarketCapital": 847281034058075.0}, {"No": 32, "IndexSummaryID": 124292, "Date": "2019-10-22T00:00:00", "IndexCode": "FINANCE", "Previous": 1260.988, "Highest": 1270.661, "Lowest": 1256.656, "Close": 1270.661, "NumberOfStock": 90.0, "Change": 9.673, "Volume": 715216549.0, "Value": 1822068721006.0, "Frequency": 42192.0, "MarketCapital": 2380919013247850.0}, {"No": 33, "IndexSummaryID": 124293, "Date": "2019-10-22T00:00:00", "IndexCode": "TRADE", "Previous": 807.429, "Highest": 811.184, "Lowest": 805.964, "Close": 809.357, "NumberOfStock": 166.0, "Change": 1.928, "Volume": 8689222233.0, "Value": 1976044569779.0, "Frequency": 199722.0, "MarketCapital": 721082168650326.0}, {"No": 34, "IndexSummaryID": 124294, "Date": "2019-10-22T00:00:00", "IndexCode": "MANUFACTUR", "Previous": 1444.954, "Highest": 1453.109, "Lowest": 1432.778, "Close": 1447.945, "NumberOfStock": 178.0, "Change": 2.991, "Volume": 973246076.0, "Value": 1845186386968.0, "Frequency": 100136.0, "MarketCapital": 2285590348981780.0}]